pg_logidater/__init__.py
pg_logidater/cli.py
pg_logidater/exceptions.py
pg_logidater/master.py
pg_logidater/replica.py
pg_logidater/sqlqueries.py
pg_logidater/tartget.py
pg_logidater/utils.py
pg_logidater-0.3.5.dist-info/LICENSE
pg_logidater-0.3.5.dist-info/METADATA
pg_logidater-0.3.5.dist-info/WHEEL
pg_logidater-0.3.5.dist-info/entry_points.txt
pg_logidater-0.3.5.dist-info/RECORD
