Metadata-Version: 2.1
Name: pg-logidater
Version: 0.3.5
Summary: Postgresql logical replication setup utility
Home-page: https://github.com/niekosau
License: GPL-3.0-only
Keywords: postgres
Author: Arunas Grigalionis
Author-email: arunas.grigalionis@gmail.com
Requires-Python: >=3.9,<3.10
Classifier: License :: OSI Approved :: GNU General Public License v3 (GPLv3)
Classifier: Programming Language :: Python :: 3
Classifier: Programming Language :: Python :: 3.9
Requires-Dist: paramiko (>=3.4.0,<4.0.0)
Requires-Dist: psycopg2-binary (>=2.9.9,<3.0.0)
Requires-Dist: pycotore (>=0.2.0,<0.3.0)
Project-URL: Repository, https://github.com/niekosau/pg-logidater
